guillotina_amqp/__init__.py
guillotina_amqp/amqp.py
guillotina_amqp/api.py
guillotina_amqp/decorators.py
guillotina_amqp/exceptions.py
guillotina_amqp/interfaces.py
guillotina_amqp/job.py
guillotina_amqp/permissions.py
guillotina_amqp/state.py
guillotina_amqp/task_vars.py
guillotina_amqp/utils.py
guillotina_amqp/worker.py
guillotina_amqp/commands/__init__.py
guillotina_amqp/commands/worker.py
guillotina_amqp/tests/__init__.py
guillotina_amqp/tests/conftest.py
guillotina_amqp/tests/fixtures.py
guillotina_amqp/tests/mocks.py
guillotina_amqp/tests/package.py
guillotina_amqp/tests/test_amqp.py
guillotina_amqp/tests/test_api.py
guillotina_amqp/tests/test_state.py
guillotina_amqp/tests/test_utils.py
guillotina_amqp/tests/utils.py
guillotina_amqp-5.0.0.dist-info/LICENSE
guillotina_amqp-5.0.0.dist-info/METADATA
guillotina_amqp-5.0.0.dist-info/WHEEL
guillotina_amqp-5.0.0.dist-info/top_level.txt
guillotina_amqp-5.0.0.dist-info/RECORD
