Metadata-Version: 2.1
Name: guillotina-amqp
Version: 5.0.0
Summary: Integrate amqp into guillotina
Home-page: https://github.com/guillotinaweb/guillotina_amqp
Author: Nathan Van Gheem
Author-email: vangheem@gmail.com
License: BSD
Platform: UNKNOWN
Classifier: License :: OSI Approved :: BSD License
Classifier: Development Status :: 3 - Alpha
Classifier: Programming Language :: Python :: 3.7
Classifier: Topic :: Software Development :: Libraries :: Python Modules
Classifier: Topic :: Internet :: WWW/HTTP
Classifier: Intended Audience :: Developers
Requires-Dist: guillotina (<6,>=5.0.0.dev0)
Requires-Dist: aioamqp
Requires-Dist: lru-dict
Requires-Dist: aioredis
Provides-Extra: test
Requires-Dist: pytest (>=4.1.1) ; extra == 'test'
Requires-Dist: docker ; extra == 'test'
Requires-Dist: backoff ; extra == 'test'
Requires-Dist: psycopg2-binary ; extra == 'test'
Requires-Dist: pytest-asyncio (>=0.8.0) ; extra == 'test'
Requires-Dist: pytest-cov (>=2.6.1) ; extra == 'test'
Requires-Dist: coverage (>=4.4) ; extra == 'test'
Requires-Dist: pytest-docker-fixtures[rabbitmq] (==1.2.5) ; extra == 'test'
